{
  "projects": [
    {
      "id": 1,
      "project-name": "Random Quote Generator",
      "description": "Display a random quote at the click of a button",
      "technologies": [
        "HTML",
        "CSS",
        "JS"
      ],
      "live-link": "https://iamjameshall.github.io/Project1/",
      "github-link": "https://github.com/IAmJamesHall/Project1",
      "image-urls": [
        "/static/img/Project1/thumbnail.png",
        "/static/img/Project1/fullsize1.png"
      ]
    },
    {
      "id": 2,
      "project-name": "Pagination & Filtering",
      "description": "Enhance usability by paginating a list of employees and making them accessible by search",
      "technologies": [
        "HTML",
        "CSS",
        "JS"
      ],
      "live-link": "https://iamjameshall.github.io/Project2/",
      "github-link": "https://github.com/IAmJamesHall/Project2",
      "image-urls": [
        "/static/img/Project2/thumbnail.png",
        "/static/img/Project2/fullsize1.png",
        "/static/img/Project2/fullsize2.png"
      ]
    },
    {
      "id": 3,
      "project-name": "Form Interactivity & Validation",
      "description": "Make a form more engaging by adding interactivity & validation, while keeping progressive enhancement in mind",
      "technologies": [
        "HTML",
        "CSS",
        "JS"
      ],
      "live-link": "https://iamjameshall.github.io/Project3/",
      "github-link": "https://github.com/IAmJamesHall/Project3",
      "image-urls": [
        "/static/img/Project3/thumbnail.png",
        "/static/img/Project3/fullsize1.png",
        "/static/img/Project3/fullsize2.png"
      ]
    },
    {
      "id": 4,
      "project-name": "Phrase Hunter",
      "description": "3-round Hangman-style game show",
      "technologies": [
        "HTML",
        "CSS",
        "JS"
      ],
      "live-link": "https://iamjameshall.github.io/Project4/",
      "github-link": "https://github.com/IAmJamesHall/Project4",
      "image-urls": [
        "/static/img/Project4/thumbnail.png",
        "/static/img/Project4/fullsize1.png",
        "/static/img/Project4/fullsize2.png"
      ]
    },
    {
      "id": 5,
      "project-name": "Employee Directory",
      "description": "Uses public api `randomuser.me` to fetch and work with user profiles",
      "technologies": [
        "HTML",
        "CSS",
        "JS"
      ],
      "live-link": "https://iamjameshall.github.io/Project5/",
      "github-link": "https://github.com/IAmJamesHall/Project5",
      "image-urls": [
        "/static/img/Project5/thumbnail.png",
        "/static/img/Project5/fullsize1.png",
        "/static/img/Project5/fullsize2.png"
      ]
    },
    {
      "id": 6,
      "project-name": "React Gallery App",
      "description": "Gallery app that uses the Flickr API to respond to search queries",
      "technologies": [
        "ReactJS",
        "HTML",
        "CSS",
        "JS"
      ],
      "live-link": "https://iamjameshall.github.io/Project7/",
      "github-link": "https://github.com/IAmJamesHall/Project7",
      "image-urls": [
        "/static/img/Project7/thumbnail.png",
        "/static/img/Project7/fullsize1.png",
        "/static/img/Project7/fullsize2.png"
      ]
    },
    {
      "id": 7,
      "project-name": "Library database",
      "description": "Database book manager; all basic CRUD operations supported",
      "technologies": [
        "Express",
        "SQLite",
        "ExpressJS",
        "Node",
        "Pug",
        "CSS",
        "HTML"
      ],
      "live-link": "https://my-library-database.herokuapp.com/",
      "github-link": "https://github.com/IAmJamesHall/Project8",
      "image-urls": [
        "/static/img/Project8/thumbnail.png",
        "/static/img/Project8/fullsize1.png",
        "/static/img/Project8/fullsize2.png"
      ]
    },
    {
      "id": 8,
      "project-name": "Authenticated Course Manager",
      "description": "Full-stack course manager; authentication & CRUD operations supported",
      "technologies": [
        "NodeJS",
        "ReactJS",
        "SQLite",
        "CSS",
        "HTML"
      ],
      "live-link": "https://iamjameshall.github.io/Project10/#/",
      "github-link": "https://github.com/IAmJamesHall/Project10",
      "image-urls": [
        "/static/img/Project10/thumbnail.png",
        "/static/img/Project10/fullsize1.png",
        "/static/img/Project10/fullsize2.png"
      ]
    }
  ]
}